{
    "L": {
        "color": [0.8, 0.8, 0.8], 
        "bg_color": [0.1, 0.1, 0.1, 0.3],
        "trans": 100
        },
    "R": {
        "color": [1, 0.2, 0.2], 
        "bg_color": [1, 0, 0, 0.6],
        "trans": 70
        },
    "G": {
        "color": [0.2, 1, 0.2], 
        "bg_color": [0, 1, 0, 0.5],
        "trans": 65
        },
    "B": {
        "color": [0.3, 0.3, 1], 
        "bg_color": [0, 0, 1, 0.5],
        "trans": 60
        },
    "dark": {
        "color": [0, 0, 0], 
        "bg_color": [0, 0, 0, 0],
        "trans": 0
        },
    "C": {
        "color": [0.8, 0.8, 0.8], 
        "bg_color": [0.1, 0.1, 0.1, 0.3],
        "trans": 100
        },
    "H": {
        "color": [0.8, 0.3, 0.3], 
        "bg_color": [1, 0.6, 0.6, 0.5],
        "trans": 25
        },
    "O": {
        "color": [0.2, 0.6, 0.8], 
        "bg_color": [0, 0, 0, 0],
        "trans": 23
        },
    "S": {
        "color": [0.1, 0.8, 0.4], 
        "bg_color": [0, 0, 0, 0],
        "trans": 15
        },
    "spec": {
        "color": [0.7, 0.6, 0.2], 
        "bg_color": [0, 0, 0, 0],
        "trans": 30
        },
    "-": {
        "color": [0.15, 0.15, 0.15], 
        "bg_color": [0, 0, 0, 0],
        "trans": 0
        },
    "?": {
        "color": [0.15, 0.15, 0.15], 
        "bg_color": [0, 0, 0, 0],
        "trans": 0
        }
}
